ggbpackage/__init__.py
ggbpackage/dop.py
ggbpackage/main.py
ggbpackage-0.0.1.dist-info/METADATA
ggbpackage-0.0.1.dist-info/WHEEL
ggbpackage-0.0.1.dist-info/top_level.txt
ggbpackage-0.0.1.dist-info/RECORD
