Metadata-Version: 2.1
Name: ggbpackage
Version: 0.0.1
Summary: My package1
Home-page: https://github.com/ericjaychi/sample-pypi-package
Author: Daniil Ruzhkov
Author-email: d.ruzhkov7@gmail.com
License: UNKNOWN
Platform: UNKNOWN
Classifier: Programming Language :: Python :: 3.8
Classifier: License :: OSI Approved :: MIT License
Classifier: Operating System :: OS Independent
Requires-Python: >=3.6
